gentune_flan/__init__.py
gentune_flan/optimize_flan_t5_base.py
gentune_flan/optimize_flan_t5_large.py
gentune_flan/optimize_flan_t5_small.py
gentune_flan-0.1.8.dist-info/licenses/LICENSE
gentune_flan-0.1.8.dist-info/METADATA
gentune_flan-0.1.8.dist-info/WHEEL
gentune_flan-0.1.8.dist-info/top_level.txt
gentune_flan-0.1.8.dist-info/RECORD
