Metadata-Version: 2.4
Name: gentune_flan
Version: 0.1.8
Summary: Genetic Algorithm: Optimize the finetuning of FLAN-T5 models
Home-page: https://github.com/manishagrawal-datascience/gentune_flan.git
Author: Manish Agrawal
Author-email: manishagrawal.datascience@gmail.com
Classifier: Programming Language :: Python :: 3
Classifier: License :: OSI Approved :: MIT License
Classifier: Operating System :: OS Independent
Requires-Python: >=3.6
License-File: LICENSE
Requires-Dist: transformers>=2.53.1
Requires-Dist: evaluate>=0.4.5
Requires-Dist: numpy>=2.0.2
Requires-Dist: pandas>=2.2.2
Requires-Dist: rouge_score>=0.1.2
Dynamic: author
Dynamic: author-email
Dynamic: classifier
Dynamic: description
Dynamic: description-content-type
Dynamic: home-page
Dynamic: license-file
Dynamic: requires-dist
Dynamic: requires-python
Dynamic: summary
